vfscript/__init__.py
vfscript/__main__.py
vfscript/config.py
vfscript/core.py
vfscript/input_params.json
vfscript/cluster_processing/__init__.py
vfscript/cluster_processing/cluster_macth.py
vfscript/cluster_processing/cluster_processor.py
vfscript/cluster_processing/cluster_processor_machine.py
vfscript/cluster_processing/export_cluster_list.py
vfscript/cluster_processing/key_files_separator.py
vfscript/runner/__init__.py
vfscript/runner/finger_runner.py
vfscript/runner/vacancy_runner.py
vfscript/surface_processor/__init__.py
vfscript/surface_processor/cluster_dump_processor.py
vfscript/surface_processor/surface_processor.py
vfscript/training/__init__.py
vfscript/training/cristal_structure_gen.py
vfscript/training/synthetic_data.py
vfscript/training/training_fingerstyle.py
vfscript/training/training_processor.py
vfscript/training/utils.py
vfscript/training/vacancy_predictor_curve.py
vfscript/training/vacancy_predictors.py
vfscript/utils/__init__.py
vfscript/utils/io_utils.py
vfscript/utils/utilidades_clustering.py
vfscript-0.1.8.dist-info/METADATA
vfscript-0.1.8.dist-info/WHEEL
vfscript-0.1.8.dist-info/entry_points.txt
vfscript-0.1.8.dist-info/top_level.txt
vfscript-0.1.8.dist-info/RECORD
